chat_completion_server/__init__.py
chat_completion_server/main.py
chat_completion_server/core/__init__.py
chat_completion_server/core/constants.py
chat_completion_server/core/logging.py
chat_completion_server/core/model_manager.py
chat_completion_server/core/normalizer.py
chat_completion_server/core/proxy_handler.py
chat_completion_server/core/server.py
chat_completion_server/core/tool_use.py
chat_completion_server/models/__init__.py
chat_completion_server/models/config.py
chat_completion_server/models/model.py
chat_completion_server/models/plugin.py
chat_completion_server/plugins/__init__.py
chat_completion_server/plugins/guardrails.py
chat_completion_server/plugins/logging.py
chat_completion_server/services/__init__.py
chat_completion_server-0.2.4.dist-info/METADATA
chat_completion_server-0.2.4.dist-info/WHEEL
chat_completion_server-0.2.4.dist-info/top_level.txt
chat_completion_server-0.2.4.dist-info/RECORD
